drive_screen/__init__.py
drive_screen/alarm_api.py
drive_screen/alarm_panel.py
drive_screen/alarm_panel_callback_decorator.py
drive_screen/alarm_panel_callbacks.py
drive_screen/alarm_panel_layout.py
drive_screen/static/style.css
drive_screen/style.py
drive_screen-0.2.2.dist-info/WHEEL
drive_screen-0.2.2.dist-info/METADATA
drive_screen-0.2.2.dist-info/RECORD
