Metadata-Version: 2.1
Name: drive-screen
Version: 0.2.2
Summary: downgrade the python version require
Author: shengqin ding
Author-email: dshengq@163.com
Requires-Python: >=3.6,<4.0
Classifier: Programming Language :: Python :: 3
Classifier: Programming Language :: Python :: 3.6
Classifier: Programming Language :: Python :: 3.7
Classifier: Programming Language :: Python :: 3.8
Classifier: Programming Language :: Python :: 3.9
Classifier: Programming Language :: Python :: 3.10
Requires-Dist: Flask (>=2.0.1,<3.0.0)
Requires-Dist: Pillow (>=9.2.0,<10.0.0)
Requires-Dist: PyMySQL (>=1.0.2,<2.0.0)
Requires-Dist: dash (>=2.0.0,<3.0.0)
Requires-Dist: dash-core-components (>=2.0.0,<3.0.0)
Requires-Dist: dash-html-components (>=2.0.0,<3.0.0)
Requires-Dist: dash_bootstrap_components (>=1.2.1,<2.0.0)
Requires-Dist: pandas (>=1.1.5,<2.0.0)
Requires-Dist: plotly (>=5.2.1,<6.0.0)
Requires-Dist: requests (>=2.27.1,<3.0.0)
